qenc.py
qencoder/av1anworkarounds.py
qencoder/mainwindow.py
qencoder/window.py
qencoder-2.1.4.dist-info/LICENSE
qencoder-2.1.4.dist-info/METADATA
qencoder-2.1.4.dist-info/WHEEL
qencoder-2.1.4.dist-info/entry_points.txt
qencoder-2.1.4.dist-info/top_level.txt
qencoder-2.1.4.dist-info/RECORD
