Metadata-Version: 2.1
Name: qencoder
Version: 2.1.4
Summary: Qt graphical interface for encoding
Home-page: https://github.com/natis1/qencoder
Author: Eli Stone
Author-email: eli.stonium@gmail.com
License: UNKNOWN
Platform: UNKNOWN
Classifier: Programming Language :: Python :: 3
Classifier: License :: OSI Approved :: GNU General Public License v3 or later (GPLv3+)
Classifier: Operating System :: OS Independent
Requires-Python: >=3.7
Requires-Dist: Av1an
Requires-Dist: PyQt5
Requires-Dist: psutil
